monai/deploy/__init__.py
monai/deploy/_version.py
monai_app_sdk-0.0.0.dist-info/LICENSE
monai_app_sdk-0.0.0.dist-info/METADATA
monai_app_sdk-0.0.0.dist-info/WHEEL
monai_app_sdk-0.0.0.dist-info/top_level.txt
monai_app_sdk-0.0.0.dist-info/RECORD
