Metadata-Version: 2.1
Name: monai-app-sdk
Version: 0.0.0
Summary: A framework and associated tools to design, verify and analyze performance of MONAI apps
Home-page: https://monai.io/
Author: MONAI Consortium
Author-email: monai.contact@gmail.com
License: Apache License 2.0
Project-URL: Documentation, https://docs.monai.io/
Project-URL: Bug Tracker, https://github.com/Project-MONAI/monai-app-sdk/issues
Project-URL: Source Code, https://github.com/Project-MONAI/monai-app-sdk
Platform: OS Independent
Requires-Python: >=3.6
License-File: LICENSE
Requires-Dist: numpy (>=1.17)
Provides-Extra: all
Requires-Dist: cucim (~=21.06) ; extra == 'all'
Provides-Extra: cucim
Requires-Dist: cucim (~=21.06) ; extra == 'cucim'
